playwright_captcha/__init__.py
playwright_captcha/captchas/__init__.py
playwright_captcha/captchas/cloudflare_interstitial/__init__.py
playwright_captcha/captchas/cloudflare_interstitial/apply.py
playwright_captcha/captchas/cloudflare_interstitial/detect_data.py
playwright_captcha/captchas/cloudflare_interstitial/solvers/__init__.py
playwright_captcha/captchas/cloudflare_interstitial/solvers/click.py
playwright_captcha/captchas/cloudflare_interstitial/solvers/twocaptcha.py
playwright_captcha/captchas/cloudflare_turnstile/__init__.py
playwright_captcha/captchas/cloudflare_turnstile/apply.py
playwright_captcha/captchas/cloudflare_turnstile/detect_data.py
playwright_captcha/captchas/cloudflare_turnstile/solvers/__init__.py
playwright_captcha/captchas/cloudflare_turnstile/solvers/click.py
playwright_captcha/captchas/cloudflare_turnstile/solvers/twocaptcha.py
playwright_captcha/captchas/image/__init__.py
playwright_captcha/captchas/image/apply.py
playwright_captcha/captchas/image/detect_data.py
playwright_captcha/captchas/image/solvers/capsolver.py
playwright_captcha/captchas/image/solvers/tencaptcha.py
playwright_captcha/captchas/recaptcha_v2/__init__.py
playwright_captcha/captchas/recaptcha_v2/apply.py
playwright_captcha/captchas/recaptcha_v2/detect_data.py
playwright_captcha/captchas/recaptcha_v2/solvers/__init__.py
playwright_captcha/captchas/recaptcha_v2/solvers/capsolver.py
playwright_captcha/captchas/recaptcha_v2/solvers/captchaai.py
playwright_captcha/captchas/recaptcha_v2/solvers/tencaptcha.py
playwright_captcha/captchas/recaptcha_v2/solvers/twocaptcha.py
playwright_captcha/captchas/recaptcha_v3/__init__.py
playwright_captcha/captchas/recaptcha_v3/apply.py
playwright_captcha/captchas/recaptcha_v3/detect_data.py
playwright_captcha/captchas/recaptcha_v3/solvers/__init__.py
playwright_captcha/captchas/recaptcha_v3/solvers/capsolver.py
playwright_captcha/captchas/recaptcha_v3/solvers/captchaai.py
playwright_captcha/captchas/recaptcha_v3/solvers/tencaptcha.py
playwright_captchax-0.1.4.dist-info/licenses/LICENSE
playwright_captchax-0.1.4.dist-info/METADATA
playwright_captchax-0.1.4.dist-info/WHEEL
playwright_captchax-0.1.4.dist-info/top_level.txt
playwright_captchax-0.1.4.dist-info/RECORD
