Metadata-Version: 2.4
Name: playwright-captchax
Version: 0.1.4
Summary: Automating captcha solving for Playwright. Supports Cloudflare Turnstile & Interstitial, and reCAPTCHA V2 & V3 with Click-based or API (2captcha) solving. Designed for easy integration with Playwright, Patchright, and Camoufox.
Author-email: Chasty <contact@chasty.dev>
License-Expression: MIT
Project-URL: Homepage, https://github.com/chasty/playwright-captcha
Project-URL: Repository, https://github.com/chasty/playwright-captcha
Project-URL: Issues, https://github.com/chasty/playwright-captcha/issues
Requires-Python: >=3.8
License-File: LICENSE
Requires-Dist: 2captcha-python-async
Provides-Extra: dev
Requires-Dist: pytest>=8.4.0; extra == "dev"
Requires-Dist: pytest-asyncio>=1.0.0; extra == "dev"
Requires-Dist: pytest-cov>=6.1.1; extra == "dev"
Dynamic: license-file
